[
  {
    "precedes_step_id": "step-1",
    "name": "step-1",
    "workflow_step": "legal-clearance",
    "step_number": 32,
    "display_name": "Legal Clearance"
  },
  {
    "precedes_step_id": "step-2",
    "name": "step-2",
    "workflow_step": "release-approval-gate",
    "step_number": 33,
    "display_name": "Release Approval Gate"
  },
  {
    "precedes_step_id": "step-3",
    "name": "step-3",
    "workflow_step": "deployment-execution",
    "step_number": 34,
    "display_name": "Deployment Execution"
  },
  {
    "precedes_step_id": "step-4",
    "name": "step-4",
    "workflow_step": "post-deployment-review",
    "step_number": 35,
    "display_name": "Post Deployment Review"
  },
  {
    "precedes_step_id": "step-5",
    "name": "step-5",
    "workflow_step": "",
    "step_number": 36,
    "display_name": null
  }
]